click_command_tree.py
click_command_tree-1.1.1.dist-info/LICENSE
click_command_tree-1.1.1.dist-info/METADATA
click_command_tree-1.1.1.dist-info/WHEEL
click_command_tree-1.1.1.dist-info/entry_points.txt
click_command_tree-1.1.1.dist-info/top_level.txt
click_command_tree-1.1.1.dist-info/RECORD
