Metadata-Version: 2.1
Name: click-command-tree
Version: 1.1.1
Summary: click plugin to show the command tree of your CLI
Home-page: https://github.com/whwright/click-command-tree
Author: Harrison Wright
Author-email: mail@harrisonwright.me
License: MIT
Classifier: License :: OSI Approved :: MIT License
Classifier: Programming Language :: Python :: 3
License-File: LICENSE
Requires-Dist: click
